CHANGELOG.txt
LICENSE.txt
MANIFEST.in
README.txt
setup.py
AdCalc/__init__.py
AdCalc/lcm.py
AdCalc/main.py
AdCalc.egg-info/PKG-INFO
AdCalc.egg-info/SOURCES.txt
AdCalc.egg-info/dependency_links.txt
AdCalc.egg-info/top_level.txt